frechet_coefficient/__init__.py
frechet_coefficient/cli.py
frechet_coefficient/metrics.py
frechet_coefficient/models_tensorflow.py
frechet_coefficient/models_torch.py
frechet_coefficient/utils.py
frechet_coefficient-2.0.13.dist-info/METADATA
frechet_coefficient-2.0.13.dist-info/WHEEL
frechet_coefficient-2.0.13.dist-info/entry_points.txt
frechet_coefficient-2.0.13.dist-info/licenses/LICENSE
frechet_coefficient-2.0.13.dist-info/RECORD
