Metadata-Version: 2.4
Name: frechet-coefficient
Version: 2.0.13
Summary: Frechet Coefficient
Project-URL: Homepage, https://github.com/adriankucharski/frechet-coefficient
Project-URL: Documentation, https://github.com/adriankucharski/frechet-coefficient
Project-URL: Repository, https://github.com/adriankucharski/frechet-coefficient
Author: Adrian Kucharski
Maintainer: Adrian Kucharski
License: MIT License
License-File: LICENSE
Keywords: fid,frechet,frechet-coefficient
Requires-Python: <3.13,>=3.9
Requires-Dist: imageio>=2.29.0
Requires-Dist: numpy>=1.21.0
Provides-Extra: tensorflow
Requires-Dist: tensorflow[and-cuda]>=2.16.0; extra == 'tensorflow'
Provides-Extra: torch
Requires-Dist: torch>=2.0.0; extra == 'torch'
Requires-Dist: torchvision>=0.15; extra == 'torch'
Requires-Dist: tqdm; extra == 'torch'
Requires-Dist: transformers; extra == 'torch'
